main.py
pickaxe_mcp_open_alex-0.1.4.dist-info/METADATA
pickaxe_mcp_open_alex-0.1.4.dist-info/WHEEL
pickaxe_mcp_open_alex-0.1.4.dist-info/entry_points.txt
pickaxe_mcp_open_alex-0.1.4.dist-info/top_level.txt
pickaxe_mcp_open_alex-0.1.4.dist-info/RECORD
